dashboard_lego/__init__.py
dashboard_lego/blocks/__init__.py
dashboard_lego/blocks/base.py
dashboard_lego/blocks/control_panel.py
dashboard_lego/blocks/metrics_factory.py
dashboard_lego/blocks/single_metric.py
dashboard_lego/blocks/text.py
dashboard_lego/blocks/typed_chart.py
dashboard_lego/core/__init__.py
dashboard_lego/core/chart_context.py
dashboard_lego/core/data_builder.py
dashboard_lego/core/data_transformer.py
dashboard_lego/core/datasource.py
dashboard_lego/core/page.py
dashboard_lego/core/preprocessor.py
dashboard_lego/core/processing_context.py
dashboard_lego/core/sidebar.py
dashboard_lego/core/state.py
dashboard_lego/core/theme.py
dashboard_lego/core/datasources/__init__.py
dashboard_lego/core/datasources/csv_source.py
dashboard_lego/core/datasources/parquet_source.py
dashboard_lego/core/datasources/sql_source.py
dashboard_lego/presets/__init__.py
dashboard_lego/presets/control_styles.py
dashboard_lego/presets/eda_presets.py
dashboard_lego/presets/layouts.py
dashboard_lego/presets/ml_presets.py
dashboard_lego/utils/__init__.py
dashboard_lego/utils/comparison_plots.py
dashboard_lego/utils/exceptions.py
dashboard_lego/utils/formatting.py
dashboard_lego/utils/logger.py
dashboard_lego/utils/plot_functions.py
dashboard_lego/utils/plot_registry.py
dashboard_lego-0.15.1.dist-info/licenses/LICENSE
dashboard_lego-0.15.1.dist-info/METADATA
dashboard_lego-0.15.1.dist-info/WHEEL
dashboard_lego-0.15.1.dist-info/top_level.txt
dashboard_lego-0.15.1.dist-info/RECORD
