Metadata-Version: 2.4
Name: dashboard-lego
Version: 0.15.1
Summary: A modular Python library for building interactive dashboards using Dash and Plotly
Author-email: Vitalii Voronov <myrdhin.yates@gmail.com>
Maintainer-email: Vitalii Voronov <myrdhin.yates@gmail.com>
License: MIT
Project-URL: Homepage, https://github.com/blghtr/dashboard_lego
Project-URL: Documentation, https://blghtr.github.io/dashboard_lego/
Project-URL: Repository, https://github.com/blghtr/dashboard_lego
Project-URL: Bug Tracker, https://github.com/blghtr/dashboard_lego/issues
Project-URL: Changelog, https://github.com/blghtr/dashboard_lego/blob/main/CHANGELOG.md
Keywords: dashboard,dash,plotly,data-visualization,eda
Classifier: Development Status :: 4 - Beta
Classifier: Intended Audience :: Developers
Classifier: Intended Audience :: Science/Research
Classifier: License :: OSI Approved :: MIT License
Classifier: Operating System :: OS Independent
Classifier: Programming Language :: Python :: 3
Classifier: Programming Language :: Python :: 3.10
Classifier: Programming Language :: Python :: 3.11
Classifier: Topic :: Scientific/Engineering :: Visualization
Classifier: Topic :: Software Development :: Libraries :: Python Modules
Requires-Python: <3.12,>=3.10
License-File: LICENSE
Requires-Dist: dash>=2.14.0
Requires-Dist: dash-bootstrap-components>=1.5.0
Requires-Dist: plotly>=5.17.0
Requires-Dist: pandas>=2.0.0
Requires-Dist: numpy>=1.24.0
Requires-Dist: diskcache>=5.6.0
Requires-Dist: pyarrow>=14.0.0
Requires-Dist: sqlalchemy>=2.0.43
Requires-Dist: scikit-learn>=1.6.1
Requires-Dist: isort>=6.0.1
Provides-Extra: dev
Requires-Dist: dash[testing]>=2.14.0; extra == "dev"
Requires-Dist: pytest>=7.4.0; extra == "dev"
Requires-Dist: pytest-cov>=4.1.0; extra == "dev"
Requires-Dist: pytest-mock; extra == "dev"
Requires-Dist: black>=23.0.0; extra == "dev"
Requires-Dist: flake8>=6.0.0; extra == "dev"
Requires-Dist: mypy>=1.5.0; extra == "dev"
Requires-Dist: pre-commit>=3.4.0; extra == "dev"
Provides-Extra: docs
Requires-Dist: sphinx>=7.1.0; extra == "docs"
Requires-Dist: sphinx-rtd-theme>=1.3.0; extra == "docs"
Provides-Extra: ml
Requires-Dist: scipy>=1.11.1; extra == "ml"
Requires-Dist: scikit-learn>=1.3.0; extra == "ml"
Provides-Extra: sql
Requires-Dist: sqlalchemy>=2.0.0; extra == "sql"
Dynamic: license-file
